{
  "demographicStr": "the patient is a man, born on January 1, 1963 (age 60)",
  "conditionHistory": [],
  "currentAllergies": [],
  "currentConditions": [
    {
      "uuid": "cond1",
      "label": "Hypertension",
      "code": "I10"
    },
    {
      "uuid": "cond2",
      "label": "Type 2 diabetes mellitus without complications",
      "code": "E11.9"
    },
    {
      "uuid": "cond3",
      "label": "Hyperlipidemia",
      "code": "E78.5"
    }
  ],
  "currentGoals": [
    {
      "uuid": "goal1",
      "label": "Improve blood sugar control",
      "code": ""
    },
    {
      "uuid": "goal2",
      "label": "Manage blood pressure",
      "code": ""
    },
    {
      "uuid": "goal3",
      "label": "Lower cholesterol levels",
      "code": ""
    }
  ],
  "currentMedications": [
    {
      "uuid": "med1",
      "label": "Lisinopril 10 mg tablet",
      "code": "314076"
    },
    {
      "uuid": "med2",
      "label": "Metformin 500 mg tablet",
      "code": "860975"
    },
    {
      "uuid": "med3",
      "label": "Atorvastatin 20 mg tablet",
      "code": "617317"
    }
  ],
  "familyHistory": [
    {
      "uuid": "fh1",
      "label": "Family history of cardiovascular disease",
      "code": "Z82.49"
    }
  ],
  "surgeryHistory": []
}