[
  {
    "criterion": "Reward for documenting the patient's report of nausea and its comparison to previous experiences with fluoxetine.",
    "weight": 20,
    "sense": "positive"
  },
  {
    "criterion": "Reward for noting the patient's slight improvement in anxiety symptoms since starting sertraline.",
    "weight": 15,
    "sense": "positive"
  },
  {
    "criterion": "Penalize for omitting a plan to follow up on the patient's nausea and potential need for medication adjustment if symptoms persist.",
    "weight": 25,
    "sense": "negative"
  },
  {
    "criterion": "Reward for including the patient's strategy of taking sertraline with food to mitigate nausea.",
    "weight": 10,
    "sense": "positive"
  },
  {
    "criterion": "Penalize for not addressing the impact of school stress on the patient's anxiety and overall treatment plan.",
    "weight": 15,
    "sense": "negative"
  },
  {
    "criterion": "Reward for discussing potential future adjustments to medication dosage or timing based on symptom persistence.",
    "weight": 15,
    "sense": "positive"
  }
]