{
  "stagedCommands": {
    "reasonForVisit": [
      {
        "uuid": "sample-uuid-1",
        "label": "Medication Management Visit",
        "code": "MMV-001"
      }
    ]
  },
  "demographicStr": "the patient is a male, born on 1975-01-01 (age 48)",
  "currentConditions": [
    {
      "uuid": "cond-uuid-1",
      "label": "Hyperlipidemia",
      "code": "E78.5"
    },
    {
      "uuid": "cond-uuid-2",
      "label": "Anxiety",
      "code": "F41.9"
    }
  ],
  "currentMedications": [
    {
      "uuid": "med-uuid-1",
      "label": "Sertraline 50 mg tablet",
      "code": "219483"
    },
    {
      "uuid": "med-uuid-2",
      "label": "Atorvastatin 20 mg tablet",
      "code": "197361"
    }
  ],
  "currentAllergies": [
    {
      "uuid": "allergy-uuid-1",
      "label": "Latex",
      "code": "300913"
    }
  ],
  "surgeryHistory": [],
  "familyHistory": []
}